veux/__init__.py
veux/__main__.py
veux/config.py
veux/elements.py
veux/errors.py
veux/model.py
veux/parser.py
veux/section.py
veux/server.py
veux/stack.py
veux/stacks.py
veux/state.py
veux/stress.py
veux/tcl.py
veux/assets/__init__.py
veux/assets/chrystals_moment.stl
veux/assets/pointer_arrows.glb
veux/canvas/canvas.py
veux/canvas/gltf.py
veux/canvas/mpl.py
veux/canvas/ply.py
veux/canvas/tri.py
veux/detail/__init__.py
veux/frame/__init__.py
veux/frame/_element.py
veux/frame/_extrude_old.py
veux/frame/_section.py
veux/frame/extrude.py
veux/motion/__init__.py
veux/motion/frame.py
veux/motion/motion2.py
veux/motion/motion3.py
veux/plane/__init__.py
veux/utility/__init__.py
veux/utility/alpha_shape.py
veux/utility/alpha_shape2.py
veux/utility/consolidate.py
veux/utility/earcut.py
veux/utility/earcut2.py
veux/utility/earcut3.py
veux/utility/earcut4.py
veux/utility/earcut5.py
veux/viewer/__init__.py
veux/viewer/__main__.py
veux/viewer/babylon.html
veux/viewer/controls.css
veux/viewer/controls.js
veux/viewer/model-viewer.min.js
veux/viewer/three-130.html
veux/viewer/three-160.html
veux/viewer/three-170.html
veux/viewer/webgl_instancing_scatter.html
veux-0.0.40.dist-info/METADATA
veux-0.0.40.dist-info/WHEEL
veux-0.0.40.dist-info/entry_points.txt
veux-0.0.40.dist-info/top_level.txt
veux-0.0.40.dist-info/RECORD
