Metadata-Version: 2.4
Name: veux
Version: 0.0.40
Summary: Fast and friendly finite element visualization for xara and OpenSees/OpenSeesPy.
Author-email: "Claudio M. Perez" <50180406+claudioperez@users.noreply.github.com>
Project-URL: Repository, https://github.com/STAIRLab/veux
Project-URL: Documentation, https://veux.io
Project-URL: Examples, https://gallery.stairlab.io
Keywords: visualization,rendering,finite-rotations,post-processing,finite-element-analysis,xara,opensees,openseespy,3D,glTF
Classifier: Development Status :: 4 - Beta
Classifier: Intended Audience :: Science/Research
Classifier: Intended Audience :: Developers
Classifier: Programming Language :: C
Classifier: Programming Language :: Python
Classifier: Programming Language :: Python :: 3
Classifier: Programming Language :: Python :: 3.7
Classifier: Programming Language :: Python :: 3.8
Classifier: Programming Language :: Python :: 3.9
Classifier: Programming Language :: Python :: 3.10
Classifier: Programming Language :: Python :: 3.11
Classifier: Programming Language :: Python :: 3.12
Classifier: Programming Language :: Python :: 3 :: Only
Classifier: Topic :: Software Development
Classifier: Topic :: Scientific/Engineering
Classifier: Operating System :: Microsoft :: Windows
Classifier: Operating System :: POSIX
Classifier: Operating System :: Unix
Classifier: Operating System :: MacOS
Requires-Dist: opensees>=0.1.8
Requires-Dist: quakeio
Requires-Dist: bottle
Requires-Dist: openbim
Requires-Dist: pyyaml
Requires-Dist: scipy
Requires-Dist: numpy
Requires-Dist: plotly
Requires-Dist: xara
Requires-Dist: pygltflib
Requires-Dist: colorcet
Requires-Dist: shps>=0.0.28
